cfnv1a.cpython-37m-darwin.so
cfnv1a-0.1.3.dist-info/LICENSE
cfnv1a-0.1.3.dist-info/METADATA
cfnv1a-0.1.3.dist-info/WHEEL
cfnv1a-0.1.3.dist-info/top_level.txt
cfnv1a-0.1.3.dist-info/RECORD
